Metadata-Version: 2.1
Name: imfacesnap
Version: 0.0.0.4.2
Author: Kevin Snap
License: License :: OSI Approved :: MIT License
Classifier: Programming Language :: Python
Requires-Python: >=3.5.5
License-File: LICENSE
Requires-Dist: deepfacesnap==0.0.2
